sbml2hyb/Hmod.py
sbml2hyb/__init__.py
sbml2hyb/create_executable_windows.py
sbml2hyb/hmod_parser.py
sbml2hyb/hmod_validator.py
sbml2hyb/neural_network_parser.py
sbml2hyb/sbml2hyb.py
sbml2hyb/xml_parser.py
sbml2hyb/xml_validator.py
sbml2hyb-1.0.3.dist-info/LICENSE
sbml2hyb-1.0.3.dist-info/METADATA
sbml2hyb-1.0.3.dist-info/WHEEL
sbml2hyb-1.0.3.dist-info/top_level.txt
sbml2hyb-1.0.3.dist-info/RECORD
