Metadata-Version: 2.1
Name: sbml2hyb
Version: 1.0.3
Summary: sbml2hyb is a Pyton tool for SBML compatible hybrid modelling.
Home-page: https://github.com/r-costa/sbml2hyb
Download-URL: https://github.com/r-costa/sbml2hyb
Author: Rafael Costa
Author-email: rs.costa@fct.unl.pt
Keywords: python,converter,gui,neural-network,interface,systems-biology,hybrid-model,keras-tensorflow,sbml-model
Classifier: Development Status :: 5 - Production/Stable
Classifier: Programming Language :: Python :: 3.7
Classifier: License :: OSI Approved :: GNU Affero General Public License v3
Classifier: Operating System :: OS Independent
License-File: LICENSE
Requires-Dist: Pillow (==9.0)
Requires-Dist: tensorflow (==2.10.0)
Requires-Dist: python-libsbml (==5.19.6)
